LICENSE-APACHE
LICENSE-MIT
MANIFEST.in
NOTICE
README.md
setup.py
action/ui/docs/assets/img/banner.png
action/ui/docs/assets/img/details.png
action/ui/docs/assets/img/home.png
action/ui/docs/assets/img/napkins.png
action/ui/docs/assets/img/pdf.png
action/ui/docs/assets/img/references.png
action/ui/docs/assets/img/registration.png
action/ui/docs/assets/img/notes/abate-2012-table-1.png
action/ui/docs/assets/img/notes/abate-2012-table-2.png
action/ui/docs/assets/img/notes/dietrich-mrs19-table-1.png
action/ui/docs/assets/img/notes/table-1-cudf-solvers-abate-2020.png
action/ui/docs/assets/img/notes/table-1-optimization-criteria-abate-2013.png
action/ui/docs/assets/img/notes/table-2-cudf-solvers-abate-2020.png
action/ui/docs/assets/img/notes/wiese-scientific-problems.png
action/ui/docs/assets/img/notes/wiese-social-problems.png
action/ui/docs/assets/img/notes/wiese-technical-problems.png
spack-opt/spack/linux-ubuntu20.04-skylake/gcc-9.4.0/cmake-3.23.2-qtdgoyb3deyzip5iy7se3tld2w7esaqq/share/cmake-3.23/Templates/Windows/ApplicationIcon.png
spack-opt/spack/linux-ubuntu20.04-skylake/gcc-9.4.0/cmake-3.23.2-qtdgoyb3deyzip5iy7se3tld2w7esaqq/share/cmake-3.23/Templates/Windows/Logo.png
spack-opt/spack/linux-ubuntu20.04-skylake/gcc-9.4.0/cmake-3.23.2-qtdgoyb3deyzip5iy7se3tld2w7esaqq/share/cmake-3.23/Templates/Windows/SmallLogo.png
spack-opt/spack/linux-ubuntu20.04-skylake/gcc-9.4.0/cmake-3.23.2-qtdgoyb3deyzip5iy7se3tld2w7esaqq/share/cmake-3.23/Templates/Windows/SmallLogo44x44.png
spack-opt/spack/linux-ubuntu20.04-skylake/gcc-9.4.0/cmake-3.23.2-qtdgoyb3deyzip5iy7se3tld2w7esaqq/share/cmake-3.23/Templates/Windows/SplashScreen.png
spack-opt/spack/linux-ubuntu20.04-skylake/gcc-9.4.0/cmake-3.23.2-qtdgoyb3deyzip5iy7se3tld2w7esaqq/share/cmake-3.23/Templates/Windows/StoreLogo.png
spack-opt/spack/linux-ubuntu20.04-skylake/gcc-9.4.0/libxml2-2.9.13-m7ke63ak62hdyael7tf36h2cg7vilwxl/share/doc/libxml2/html/w3c.png
spliced.egg-info/PKG-INFO
spliced.egg-info/SOURCES.txt
spliced.egg-info/dependency_links.txt
spliced.egg-info/entry_points.txt
spliced.egg-info/not-zip-safe
spliced.egg-info/requires.txt
spliced.egg-info/top_level.txt
