Metadata-Version: 2.1
Name: spliced
Version: 0.0.17
Summary: Emulate or predict splicing outcomes.
Home-page: https://github.com/buildsi/spliced
Author: Vanessa Sochat
Maintainer: Vanessa Sochat
License: LICENSE-MIT
Keywords: splicing,spack,packages
Platform: UNKNOWN
Classifier: Intended Audience :: Science/Research
Classifier: Intended Audience :: Developers
Classifier: License :: OSI Approved :: MIT License
Classifier: Programming Language :: Python
Classifier: Topic :: Software Development
Classifier: Topic :: Scientific/Engineering
Classifier: Operating System :: Unix
Classifier: Programming Language :: Python :: 3.8
Provides-Extra: all
License-File: LICENSE-APACHE
License-File: LICENSE-MIT
License-File: NOTICE
